gcpts/__init__.py
gcpts/dt.py
gcpts/protocol.py
gcpts/sql/__init__.py
gcpts/sql/basic.py
gcpts/sql/resample.py
gcpts/uploader.py
gcpts-0.1.2.dist-info/WHEEL
gcpts-0.1.2.dist-info/METADATA
gcpts-0.1.2.dist-info/RECORD
