Metadata-Version: 2.1
Name: gcpts
Version: 0.1.2
Summary: 
Author: richwomanbtc
Author-email: richwomanbtc@gmail.com
Requires-Python: >=3.10,<4.0
Classifier: Programming Language :: Python :: 3
Classifier: Programming Language :: Python :: 3.10
Classifier: Programming Language :: Python :: 3.11
Requires-Dist: db-dtypes (>=1.0.5,<2.0.0)
Requires-Dist: gcsfs (>=2022.11.0,<2023.0.0)
Requires-Dist: google-cloud-bigquery (>=3.4.1,<4.0.0)
Requires-Dist: pandas (>=1.5.2,<2.0.0)
Requires-Dist: pandas-gbq (>=0.19.1,<0.20.0)
Requires-Dist: pyarrow (>=10.0.1,<11.0.0)
